{
  "objective": "balanced",
  "param_mode": "group",
  "cost_sweep": [
    0.024796724319458008,
    0.530970573425293,
    0.611020565032959,
    0.6952735185623169,
    0.8003813028335571,
    0.9052590727806091,
    0.9974414110183716,
    1.0939507484436035,
    1.201464056968689,
    1.2972406148910522,
    1.356005311012268,
    1.425464153289795,
    1.460617184638977
  ],
  "results_per_cost": [
    {
      "cost": 0.024796724319458008,
      "alpha": [
        1.3799999952316284,
        0.6200000047683716
      ],
      "mu": [
        -0.5,
        0.0
      ],
      "val_metrics": {
        "selective_error": 0.0,
        "coverage": 0.00010141052771359683,
        "rejection_rate": 0.9998985894722864,
        "group_errors": [
          0.0,
          0.0
        ],
        "worst_group_error": 0.0,
        "objective_value": 0.0
      },
      "test_metrics": {
        "selective_error": 0.0,
        "coverage": 0.00011754401493817568,
        "rejection_rate": 0.9998824559850619,
        "group_errors": [
          0.0,
          0.0
        ],
        "worst_group_error": 0.0
      }
    },
    {
      "cost": 0.530970573425293,
      "alpha": [
        1.3799999952316284,
        0.6200000047683716
      ],
      "mu": [
        -0.5,
        0.0
      ],
      "val_metrics": {
        "selective_error": 0.11050355940358385,
        "coverage": 0.19652438163757324,
        "rejection_rate": 0.8034756183624268,
        "group_errors": [
          0.003835408850468782,
          0.2171717099566989
        ],
        "worst_group_error": 0.2171717099566989,
        "objective_value": 0.0
      },
      "test_metrics": {
        "selective_error": 0.10940449533021201,
        "coverage": 0.20014634132385253,
        "rejection_rate": 0.7998536586761474,
        "group_errors": [
          0.008450062833585213,
          0.21035892782683882
        ],
        "worst_group_error": 0.21035892782683882
      }
    },
    {
      "cost": 0.611020565032959,
      "alpha": [
        1.3799999952316284,
        0.6200000047683716
      ],
      "mu": [
        -0.5,
        0.0
      ],
      "val_metrics": {
        "selective_error": 0.319121843021946,
        "coverage": 0.31706461906433103,
        "rejection_rate": 0.682935380935669,
        "group_errors": [
          0.033037634347136656,
          0.6052060516967553
        ],
        "worst_group_error": 0.6052060516967553,
        "objective_value": 0.0
      },
      "test_metrics": {
        "selective_error": 0.24196178854639086,
        "coverage": 0.3345118522644043,
        "rejection_rate": 0.6654881477355957,
        "group_errors": [
          0.024628665409187664,
          0.45929491168359404
        ],
        "worst_group_error": 0.45929491168359404
      }
    },
    {
      "cost": 0.6952735185623169,
      "alpha": [
        1.3799999952316284,
        0.6200000047683716
      ],
      "mu": [
        -0.5,
        0.0
      ],
      "val_metrics": {
        "selective_error": 0.3783979268002074,
        "coverage": 0.4200331687927246,
        "rejection_rate": 0.5799668312072754,
        "group_errors": [
          0.05516407709841083,
          0.7016317765020039
        ],
        "worst_group_error": 0.7016317765020039,
        "objective_value": 0.0
      },
      "test_metrics": {
        "selective_error": 0.31459145251809956,
        "coverage": 0.4362738609313965,
        "rejection_rate": 0.5637261390686035,
        "group_errors": [
          0.053150411769048236,
          0.5760324932671509
        ],
        "worst_group_error": 0.5760324932671509
      }
    },
    {
      "cost": 0.8003813028335571,
      "alpha": [
        1.3799999952316284,
        0.6200000047683716
      ],
      "mu": [
        -0.5,
        0.0
      ],
      "val_metrics": {
        "selective_error": 0.42420998714631697,
        "coverage": 0.4943671226501465,
        "rejection_rate": 0.5056328773498535,
        "group_errors": [
          0.09561995924137928,
          0.7528000150512547
        ],
        "worst_group_error": 0.7528000150512547,
        "objective_value": 0.0
      },
      "test_metrics": {
        "selective_error": 0.3674756894697074,
        "coverage": 0.5281310558319092,
        "rejection_rate": 0.4718689441680908,
        "group_errors": [
          0.08101650938573014,
          0.6539348695536846
        ],
        "worst_group_error": 0.6539348695536846
      }
    },
    {
      "cost": 0.9052590727806091,
      "alpha": [
        1.3799999952316284,
        0.6200000047683716
      ],
      "mu": [
        -0.5,
        0.0
      ],
      "val_metrics": {
        "selective_error": 0.46883558018490373,
        "coverage": 0.5730709075927735,
        "rejection_rate": 0.42692909240722654,
        "group_errors": [
          0.15227723379027827,
          0.7853939265795292
        ],
        "worst_group_error": 0.7853939265795292,
        "objective_value": 0.0
      },
      "test_metrics": {
        "selective_error": 0.41583694184856584,
        "coverage": 0.6082626342773437,
        "rejection_rate": 0.39173736572265627,
        "group_errors": [
          0.11844480905669892,
          0.7132290746404327
        ],
        "worst_group_error": 0.7132290746404327
      }
    },
    {
      "cost": 0.9974414110183716,
      "alpha": [
        1.3799999952316284,
        0.6200000047683716
      ],
      "mu": [
        -0.5,
        0.0
      ],
      "val_metrics": {
        "selective_error": 0.5089858707887821,
        "coverage": 0.6587904930114746,
        "rejection_rate": 0.34120950698852537,
        "group_errors": [
          0.18980814137351362,
          0.8281636002040507
        ],
        "worst_group_error": 0.8281636002040507,
        "objective_value": 0.0
      },
      "test_metrics": {
        "selective_error": 0.45583140512760123,
        "coverage": 0.6773370742797852,
        "rejection_rate": 0.3226629257202148,
        "group_errors": [
          0.15478184901253822,
          0.7568809612426642
        ],
        "worst_group_error": 0.7568809612426642
      }
    },
    {
      "cost": 1.0939507484436035,
      "alpha": [
        1.3799999952316284,
        0.6200000047683716
      ],
      "mu": [
        -0.5,
        0.0
      ],
      "val_metrics": {
        "selective_error": 0.5322622957731349,
        "coverage": 0.7425002098083496,
        "rejection_rate": 0.25749979019165037,
        "group_errors": [
          0.21549993437184595,
          0.8490246571744239
        ],
        "worst_group_error": 0.8490246571744239,
        "objective_value": 0.0
      },
      "test_metrics": {
        "selective_error": 0.4942042963028715,
        "coverage": 0.7628860473632812,
        "rejection_rate": 0.23711395263671875,
        "group_errors": [
          0.1994275647513988,
          0.7889810278543442
        ],
        "worst_group_error": 0.7889810278543442
      }
    },
    {
      "cost": 1.201464056968689,
      "alpha": [
        1.3799999952316284,
        0.6200000047683716
      ],
      "mu": [
        -0.5,
        0.0
      ],
      "val_metrics": {
        "selective_error": 0.5561903306504448,
        "coverage": 0.8160136222839356,
        "rejection_rate": 0.1839863777160644,
        "group_errors": [
          0.2503116184893155,
          0.8620690428115739
        ],
        "worst_group_error": 0.8620690428115739,
        "objective_value": 0.0
      },
      "test_metrics": {
        "selective_error": 0.534132720340512,
        "coverage": 0.8586061477661133,
        "rejection_rate": 0.14139385223388667,
        "group_errors": [
          0.24768218128277936,
          0.8205832593982445
        ],
        "worst_group_error": 0.8205832593982445
      }
    },
    {
      "cost": 1.2972406148910522,
      "alpha": [
        1.3799999952316284,
        0.6200000047683716
      ],
      "mu": [
        -0.5,
        0.0
      ],
      "val_metrics": {
        "selective_error": 0.58533229613943,
        "coverage": 0.9120771408081054,
        "rejection_rate": 0.08792285919189458,
        "group_errors": [
          0.2960478852856571,
          0.8746167069932029
        ],
        "worst_group_error": 0.8746167069932029,
        "objective_value": 0.0
      },
      "test_metrics": {
        "selective_error": 0.5606365493559822,
        "coverage": 0.9315399169921875,
        "rejection_rate": 0.06846008300781248,
        "group_errors": [
          0.28116359121350526,
          0.840109507498459
        ],
        "worst_group_error": 0.840109507498459
      }
    },
    {
      "cost": 1.356005311012268,
      "alpha": [
        1.3799999952316284,
        0.6200000047683716
      ],
      "mu": [
        -0.5,
        0.0
      ],
      "val_metrics": {
        "selective_error": 0.6007592624780391,
        "coverage": 0.9534618377685546,
        "rejection_rate": 0.04653816223144536,
        "group_errors": [
          0.3199987759752085,
          0.8815197489808697
        ],
        "worst_group_error": 0.8815197489808697,
        "objective_value": 0.0
      },
      "test_metrics": {
        "selective_error": 0.5699369326511639,
        "coverage": 0.9598033905029297,
        "rejection_rate": 0.04019660949707027,
        "group_errors": [
          0.29326300681207534,
          0.8466108584902524
        ],
        "worst_group_error": 0.8466108584902524
      }
    },
    {
      "cost": 1.425464153289795,
      "alpha": [
        1.3799999952316284,
        0.6200000047683716
      ],
      "mu": [
        -0.5,
        0.0
      ],
      "val_metrics": {
        "selective_error": 0.6094739285577842,
        "coverage": 0.9763806343078614,
        "rejection_rate": 0.023619365692138627,
        "group_errors": [
          0.3336968311977561,
          0.8852510259178122
        ],
        "worst_group_error": 0.8852510259178122,
        "objective_value": 0.0
      },
      "test_metrics": {
        "selective_error": 0.5783438410797614,
        "coverage": 0.987028694152832,
        "rejection_rate": 0.012971305847167991,
        "group_errors": [
          0.30535382174691783,
          0.851333860412605
        ],
        "worst_group_error": 0.851333860412605
      }
    },
    {
      "cost": 1.460617184638977,
      "alpha": [
        1.3799999952316284,
        0.6200000047683716
      ],
      "mu": [
        -0.5,
        0.0
      ],
      "val_metrics": {
        "selective_error": 0.610572590757041,
        "coverage": 0.9868812561035156,
        "rejection_rate": 0.013118743896484375,
        "group_errors": [
          0.3345504003884197,
          0.8865947811256623
        ],
        "worst_group_error": 0.8865947811256623,
        "objective_value": 0.0
      },
      "test_metrics": {
        "selective_error": 0.5802900711935295,
        "coverage": 0.9931305885314942,
        "rejection_rate": 0.006869411468505837,
        "group_errors": [
          0.3077131145804606,
          0.8528670278065983
        ],
        "worst_group_error": 0.8528670278065983
      }
    }
  ],
  "unified_rc_curves": {
    "balanced": {
      "val": {
        "rejection_rates": [
          0.013118743896484375,
          0.023619365692138627,
          0.04653816223144536,
          0.08792285919189458,
          0.1839863777160644,
          0.25749979019165037,
          0.34120950698852537,
          0.42692909240722654,
          0.5056328773498535,
          0.5799668312072754,
          0.682935380935669,
          0.8034756183624268,
          0.9998985894722864
        ],
        "selective_errors": [
          0.610572590757041,
          0.6094739285577842,
          0.6007592624780391,
          0.58533229613943,
          0.5561903306504448,
          0.5322622957731349,
          0.5089858707887821,
          0.46883558018490373,
          0.42420998714631697,
          0.3783979268002074,
          0.319121843021946,
          0.11050355940358385,
          0.0
        ],
        "aurc": 0.36277611548717414
      },
      "test": {
        "rejection_rates": [
          0.006869411468505837,
          0.012971305847167991,
          0.04019660949707027,
          0.06846008300781248,
          0.14139385223388667,
          0.23711395263671875,
          0.3226629257202148,
          0.39173736572265627,
          0.4718689441680908,
          0.5637261390686035,
          0.6654881477355957,
          0.7998536586761474,
          0.9998824559850619
        ],
        "selective_errors": [
          0.5802900711935295,
          0.5783438410797614,
          0.5699369326511639,
          0.5606365493559822,
          0.534132720340512,
          0.4942042963028715,
          0.45583140512760123,
          0.41583694184856584,
          0.3674756894697074,
          0.31459145251809956,
          0.24196178854639086,
          0.10940449533021201,
          0.0
        ],
        "aurc": 0.32060061453905386
      }
    },
    "worst": {
      "val": {
        "rejection_rates": [
          0.013118743896484375,
          0.023619365692138627,
          0.04653816223144536,
          0.08792285919189458,
          0.1839863777160644,
          0.25749979019165037,
          0.34120950698852537,
          0.42692909240722654,
          0.5056328773498535,
          0.5799668312072754,
          0.682935380935669,
          0.8034756183624268,
          0.9998985894722864
        ],
        "selective_errors": [
          0.8865947811256623,
          0.8852510259178122,
          0.8815197489808697,
          0.8746167069932029,
          0.8620690428115739,
          0.8490246571744239,
          0.8281636002040507,
          0.7853939265795292,
          0.7528000150512547,
          0.7016317765020039,
          0.6052060516967553,
          0.2171717099566989,
          0.0
        ],
        "aurc": 0.604315752262962
      },
      "test": {
        "rejection_rates": [
          0.006869411468505837,
          0.012971305847167991,
          0.04019660949707027,
          0.06846008300781248,
          0.14139385223388667,
          0.23711395263671875,
          0.3226629257202148,
          0.39173736572265627,
          0.4718689441680908,
          0.5637261390686035,
          0.6654881477355957,
          0.7998536586761474,
          0.9998824559850619
        ],
        "selective_errors": [
          0.8528670278065983,
          0.851333860412605,
          0.8466108584902524,
          0.840109507498459,
          0.8205832593982445,
          0.7889810278543442,
          0.7568809612426642,
          0.7132290746404327,
          0.6539348695536846,
          0.5760324932671509,
          0.45929491168359404,
          0.21035892782683882,
          0.0
        ],
        "aurc": 0.5366141193608287
      }
    }
  },
  "theory_compliant": true,
  "description": "Each cost optimizes (alpha, mu) and contributes ONE point to the unified RC curve"
}