{
  "timestamp": "20251127_080519",
  "dataset": "cifar100_lt_if100",
  "routing": "dense",
  "epochs": 50,
  "experiments": [
    {
      "preset": "all",
      "balanced_acc": 0.478,
      "val_loss": 1.9455,
      "feature_dim": 24,
      "enabled_features": "FeatureConfig(per_expert=[entropy, topk_mass, residual_mass, max_probs, top_gap, cosine_sim, kl_to_mean], global=[mean_entropy, mean_class_var, std_max_conf], top_k=5)",
      "status": "success",
      "train_log_file": "results\\ablation_feature_study_complete\\logs\\train_cifar100_lt_if100_all_20251127_080519.log",
      "baseline_balanced_error": 0.5378,
      "baseline_head_error": 0.3142783975435881,
      "baseline_tail_error": 0.761269304598397,
      "plugin_balanced_aurc_balanced": 0.2620639279572566,
      "plugin_balanced_aurc_worst_group": 0.3056444082530932,
      "plugin_balanced_test_balanced_error_r0": 0.511310435234524,
      "plugin_balanced_test_head_error_r0": 0.5622362534684863,
      "plugin_balanced_test_tail_error_r0": 0.4603846170005618,
      "plugin_balanced_log_file": "results\\ablation_feature_study_complete\\logs\\plugin_balanced_cifar100_lt_if100_all_20251127_080546.log",
      "plugin_worst_aurc_balanced": 0.21851237900570952,
      "plugin_worst_aurc_worst_group": 0.23061640484248383,
      "plugin_worst_test_balanced_error_r0": 0.4798133151956615,
      "plugin_worst_test_head_error_r0": 0.4776266115484078,
      "plugin_worst_test_tail_error_r0": 0.48200001884291516,
      "plugin_worst_log_file": "results\\ablation_feature_study_complete\\logs\\plugin_worst_cifar100_lt_if100_all_20251127_080630.log"
    },
    {
      "preset": "per_expert_only",
      "balanced_acc": 0.494,
      "val_loss": 1.9217,
      "feature_dim": 21,
      "enabled_features": "FeatureConfig(per_expert=[entropy, topk_mass, residual_mass, max_probs, top_gap, cosine_sim, kl_to_mean], global=[none], top_k=5)",
      "status": "success",
      "train_log_file": "results\\ablation_feature_study_complete\\logs\\train_cifar100_lt_if100_per_expert_only_20251127_080952.log",
      "baseline_balanced_error": 0.5355,
      "baseline_head_error": 0.31355849393762075,
      "baseline_tail_error": 0.7574230582025819,
      "plugin_balanced_aurc_balanced": 0.260809850879286,
      "plugin_balanced_aurc_worst_group": 0.30305841374766596,
      "plugin_balanced_test_balanced_error_r0": 0.5105500430934701,
      "plugin_balanced_test_head_error_r0": 0.5607868823577528,
      "plugin_balanced_test_tail_error_r0": 0.4603132038291874,
      "plugin_balanced_log_file": "results\\ablation_feature_study_complete\\logs\\plugin_balanced_cifar100_lt_if100_per_expert_only_20251127_081015.log",
      "plugin_worst_aurc_balanced": 0.2186431186275647,
      "plugin_worst_aurc_worst_group": 0.2298077221431838,
      "plugin_worst_test_balanced_error_r0": 0.4758124026724534,
      "plugin_worst_test_head_error_r0": 0.46712479000320895,
      "plugin_worst_test_tail_error_r0": 0.4845000153416978,
      "plugin_worst_log_file": "results\\ablation_feature_study_complete\\logs\\plugin_worst_cifar100_lt_if100_per_expert_only_20251127_081057.log"
    },
    {
      "preset": "global_only",
      "balanced_acc": 0.495,
      "val_loss": 1.8977,
      "feature_dim": 3,
      "enabled_features": "FeatureConfig(per_expert=[none], global=[mean_entropy, mean_class_var, std_max_conf], top_k=5)",
      "status": "success",
      "train_log_file": "results\\ablation_feature_study_complete\\logs\\train_cifar100_lt_if100_global_only_20251127_081412.log",
      "baseline_balanced_error": 0.5391,
      "baseline_head_error": 0.3151444652081721,
      "baseline_tail_error": 0.7629999881595195,
      "plugin_balanced_aurc_balanced": 0.2654463246129504,
      "plugin_balanced_aurc_worst_group": 0.3130110928798166,
      "plugin_balanced_test_balanced_error_r0": 0.5129017768043849,
      "plugin_balanced_test_head_error_r0": 0.5666496781622213,
      "plugin_balanced_test_tail_error_r0": 0.45915387544654845,
      "plugin_balanced_log_file": "results\\ablation_feature_study_complete\\logs\\plugin_balanced_cifar100_lt_if100_global_only_20251127_081432.log",
      "plugin_worst_aurc_balanced": 0.23383443123193368,
      "plugin_worst_aurc_worst_group": 0.26364064105903623,
      "plugin_worst_test_balanced_error_r0": 0.48048840239806523,
      "plugin_worst_test_head_error_r0": 0.47789984332823676,
      "plugin_worst_test_tail_error_r0": 0.48307696146789364,
      "plugin_worst_log_file": "results\\ablation_feature_study_complete\\logs\\plugin_worst_cifar100_lt_if100_global_only_20251127_081516.log"
    },
    {
      "preset": "uncertainty_only",
      "balanced_acc": 0.494,
      "val_loss": 1.9164,
      "feature_dim": 8,
      "enabled_features": "FeatureConfig(per_expert=[entropy, max_probs], global=[mean_entropy, std_max_conf], top_k=5)",
      "status": "success",
      "train_log_file": "results\\ablation_feature_study_complete\\logs\\train_cifar100_lt_if100_uncertainty_only_20251127_081702.log",
      "baseline_balanced_error": 0.5362,
      "baseline_head_error": 0.31303697831134264,
      "baseline_tail_error": 0.759423080865007,
      "plugin_balanced_aurc_balanced": 0.26478561929912997,
      "plugin_balanced_aurc_worst_group": 0.3096884631104656,
      "plugin_balanced_test_balanced_error_r0": 0.5109748274786756,
      "plugin_balanced_test_head_error_r0": 0.5618726994733564,
      "plugin_balanced_test_tail_error_r0": 0.4600769554839949,
      "plugin_balanced_log_file": "results\\ablation_feature_study_complete\\logs\\plugin_balanced_cifar100_lt_if100_uncertainty_only_20251127_081713.log",
      "plugin_worst_aurc_balanced": 0.23579069124689117,
      "plugin_worst_aurc_worst_group": 0.2645898495724114,
      "plugin_worst_test_balanced_error_r0": 0.4787927601454899,
      "plugin_worst_test_head_error_r0": 0.47539322095752246,
      "plugin_worst_test_tail_error_r0": 0.48219229933345736,
      "plugin_worst_log_file": "results\\ablation_feature_study_complete\\logs\\plugin_worst_cifar100_lt_if100_uncertainty_only_20251127_081731.log"
    },
    {
      "preset": "agreement_only",
      "balanced_acc": 0.46,
      "val_loss": 1.979,
      "feature_dim": 7,
      "enabled_features": "FeatureConfig(per_expert=[cosine_sim, kl_to_mean], global=[mean_class_var], top_k=5)",
      "status": "success",
      "train_log_file": "results\\ablation_feature_study_complete\\logs\\train_cifar100_lt_if100_agreement_only_20251127_081915.log",
      "baseline_balanced_error": 0.5593,
      "baseline_head_error": 0.3263293504728467,
      "baseline_tail_error": 0.7922692739150013,
      "plugin_balanced_aurc_balanced": 0.26619731662480056,
      "plugin_balanced_aurc_worst_group": 0.3125007514549354,
      "plugin_balanced_test_balanced_error_r0": 0.5152560422336738,
      "plugin_balanced_test_head_error_r0": 0.568435169979425,
      "plugin_balanced_test_tail_error_r0": 0.46207691448792276,
      "plugin_balanced_log_file": "results\\ablation_feature_study_complete\\logs\\plugin_balanced_cifar100_lt_if100_agreement_only_20251127_081926.log",
      "plugin_worst_aurc_balanced": 0.22354457313212545,
      "plugin_worst_aurc_worst_group": 0.23721164051496996,
      "plugin_worst_test_balanced_error_r0": 0.4882547597003173,
      "plugin_worst_test_head_error_r0": 0.4890479516268066,
      "plugin_worst_test_tail_error_r0": 0.487461567773828,
      "plugin_worst_log_file": "results\\ablation_feature_study_complete\\logs\\plugin_worst_cifar100_lt_if100_agreement_only_20251127_081944.log"
    },
    {
      "preset": "minimal",
      "balanced_acc": 0.501,
      "val_loss": 1.9013,
      "feature_dim": 6,
      "enabled_features": "FeatureConfig(per_expert=[entropy, max_probs], global=[none], top_k=5)",
      "status": "success",
      "train_log_file": "results\\ablation_feature_study_complete\\logs\\train_cifar100_lt_if100_minimal_20251127_082111.log",
      "baseline_balanced_error": 0.5324,
      "baseline_head_error": 0.3121792161378208,
      "baseline_tail_error": 0.7526154411833045,
      "plugin_balanced_aurc_balanced": 0.26107592612704006,
      "plugin_balanced_aurc_worst_group": 0.30396552360744516,
      "plugin_balanced_test_balanced_error_r0": 0.5108729795998583,
      "plugin_balanced_test_head_error_r0": 0.5628563338807407,
      "plugin_balanced_test_tail_error_r0": 0.4588896253189758,
      "plugin_balanced_log_file": "results\\ablation_feature_study_complete\\logs\\plugin_balanced_cifar100_lt_if100_minimal_20251127_082120.log",
      "plugin_worst_aurc_balanced": 0.2346390419920296,
      "plugin_worst_aurc_worst_group": 0.2658632227094908,
      "plugin_worst_test_balanced_error_r0": 0.47858704517219375,
      "plugin_worst_test_head_error_r0": 0.4770433081022582,
      "plugin_worst_test_tail_error_r0": 0.48013078224212935,
      "plugin_worst_log_file": "results\\ablation_feature_study_complete\\logs\\plugin_worst_cifar100_lt_if100_minimal_20251127_082136.log"
    },
    {
      "preset": "confidence_only",
      "balanced_acc": 0.497,
      "val_loss": 1.9255,
      "feature_dim": 13,
      "enabled_features": "FeatureConfig(per_expert=[topk_mass, residual_mass, max_probs, top_gap], global=[std_max_conf], top_k=5)",
      "status": "success",
      "train_log_file": "results\\ablation_feature_study_complete\\logs\\train_cifar100_lt_if100_confidence_only_20251127_082301.log",
      "baseline_balanced_error": 0.5326,
      "baseline_head_error": 0.312565327091631,
      "baseline_tail_error": 0.752692340647822,
      "plugin_balanced_aurc_balanced": 0.26337642797034755,
      "plugin_balanced_aurc_worst_group": 0.30809779544498467,
      "plugin_balanced_test_balanced_error_r0": 0.5132841338255121,
      "plugin_balanced_test_head_error_r0": 0.5673374609107097,
      "plugin_balanced_test_tail_error_r0": 0.45923080674031447,
      "plugin_balanced_log_file": "results\\ablation_feature_study_complete\\logs\\plugin_balanced_cifar100_lt_if100_confidence_only_20251127_082310.log",
      "plugin_worst_aurc_balanced": 0.22060390321301612,
      "plugin_worst_aurc_worst_group": 0.23342345066836134,
      "plugin_worst_test_balanced_error_r0": 0.4792891145166097,
      "plugin_worst_test_head_error_r0": 0.47673204094858773,
      "plugin_worst_test_tail_error_r0": 0.4818461880846317,
      "plugin_worst_log_file": "results\\ablation_feature_study_complete\\logs\\plugin_worst_cifar100_lt_if100_confidence_only_20251127_082325.log"
    }
  ]
}